CHANGES.rst
MANIFEST.in
Makefile
README.rst
bootstrap-buildout.py
buildout.cfg
requirements.txt
screenshot.png
screenshot2.png
setup.py
zope2_bootstrap/__init__.py
zope2_bootstrap/config.py
zope2_bootstrap/configure.zcml
zope2_bootstrap/zmi.py
zope2_bootstrap.egg-info/PKG-INFO
zope2_bootstrap.egg-info/SOURCES.txt
zope2_bootstrap.egg-info/dependency_links.txt
zope2_bootstrap.egg-info/entry_points.txt
zope2_bootstrap.egg-info/not-zip-safe
zope2_bootstrap.egg-info/requires.txt
zope2_bootstrap.egg-info/top_level.txt
zope2_bootstrap/static/VlogoWhite250.gif
zope2_bootstrap/static/zopeHIres.jpg
zope2_bootstrap/templates/manage_main.dtml
zope2_bootstrap/templates/manage_page_footer.dtml
zope2_bootstrap/templates/manage_page_header.dtml
zope2_bootstrap/templates/splash.pt