Metadata-Version: 1.1
Name: zope2-bootstrap
Version: 0.2.0
Summary: ZMI Bootstrapped
Home-page: https://github.com/collective/zope2_bootstrap
Author: Alex Clark
Author-email: aclark@aclark.net
License: GPL
Keywords: Bootstrap Zope ZMI
Platform: UNKNOWN
Classifier: Programming Language :: Python :: 2.7
